parse.py
parse_with_dot_access-1.20.0.dist-info/LICENSE
parse_with_dot_access-1.20.0.dist-info/METADATA
parse_with_dot_access-1.20.0.dist-info/WHEEL
parse_with_dot_access-1.20.0.dist-info/RECORD
