Metadata-Version: 2.1
Name: parse_with_dot_access
Version: 1.20.0
Summary: a daily rebase of parse with dot access
Home-page: https://github.com/CircleOnCircles/parse
License: ISC
Author: Richard Jones
Author-email: richard@python.org
Maintainer: Wim Glenn
Maintainer-email: hey@wimglenn.com
Requires-Python: >=3.7,<4.0
Classifier: License :: OSI Approved
Classifier: Programming Language :: Python :: 3
Classifier: Programming Language :: Python :: 3.7
Classifier: Programming Language :: Python :: 3.8
Classifier: Programming Language :: Python :: 3.9
Classifier: Programming Language :: Python :: 3.10
Classifier: Programming Language :: Python :: 3.11
Classifier: Programming Language :: Python :: 3.12
Project-URL: Repository, https://github.com/CircleOnCircles/parse
